sonatype_iq_api_client/__init__.py
sonatype_iq_api_client/api_client.py
sonatype_iq_api_client/api_response.py
sonatype_iq_api_client/configuration.py
sonatype_iq_api_client/exceptions.py
sonatype_iq_api_client/py.typed
sonatype_iq_api_client/rest.py
sonatype_iq_api_client/api/__init__.py
sonatype_iq_api_client/api/advanced_search_api.py
sonatype_iq_api_client/api/application_categories_api.py
sonatype_iq_api_client/api/application_report_data_api.py
sonatype_iq_api_client/api/applications_api.py
sonatype_iq_api_client/api/audit_logs_api.py
sonatype_iq_api_client/api/auto_policy_waiver_exclusions_api.py
sonatype_iq_api_client/api/auto_policy_waivers_api.py
sonatype_iq_api_client/api/claim_components_api.py
sonatype_iq_api_client/api/component_labels_api.py
sonatype_iq_api_client/api/component_search_api.py
sonatype_iq_api_client/api/components_api.py
sonatype_iq_api_client/api/composite_source_control_api.py
sonatype_iq_api_client/api/composite_source_control_validator_api.py
sonatype_iq_api_client/api/config_crowd_api.py
sonatype_iq_api_client/api/config_jira_api.py
sonatype_iq_api_client/api/config_mail_api.py
sonatype_iq_api_client/api/config_proxy_server_api.py
sonatype_iq_api_client/api/config_reverse_proxy_authentication_api.py
sonatype_iq_api_client/api/config_saml_api.py
sonatype_iq_api_client/api/config_source_control_api.py
sonatype_iq_api_client/api/config_zscaler_api.py
sonatype_iq_api_client/api/configuration_api.py
sonatype_iq_api_client/api/configure_artifactory_connection_api.py
sonatype_iq_api_client/api/cpe_matching_configuration_api.py
sonatype_iq_api_client/api/cyclone_dx_api.py
sonatype_iq_api_client/api/data_retention_policies_api.py
sonatype_iq_api_client/api/developer_priorities_api.py
sonatype_iq_api_client/api/endpoints_api.py
sonatype_iq_api_client/api/feature_configuration_api.py
sonatype_iq_api_client/api/firewall_api.py
sonatype_iq_api_client/api/license_legal_metadata_report_api.py
sonatype_iq_api_client-0.196.1.dist-info/licenses/LICENSE
sonatype_iq_api_client-0.196.1.dist-info/METADATA
sonatype_iq_api_client-0.196.1.dist-info/WHEEL
sonatype_iq_api_client-0.196.1.dist-info/top_level.txt
sonatype_iq_api_client-0.196.1.dist-info/RECORD
