Metadata-Version: 2.4
Name: sonatype_iq_api_client
Version: 0.196.1
Summary: Sonatype Lifecycle Public REST API
Home-page: 
Author: Sonatype Community
Author-email: Sonatype Community <community@sonatype.com>
License: Apache-2.0
Project-URL: Repository, https://github.com/sonatype-nexus-community/nexus-iq-api-client
Keywords: OpenAPI,OpenAPI-Generator,Sonatype Lifecycle Public REST API
Requires-Python: >=3.9
License-File: LICENSE
Requires-Dist: urllib3<3.0.0,>=2.1.0
Requires-Dist: python-dateutil>=2.8.2
Requires-Dist: pydantic>=2
Requires-Dist: typing-extensions>=4.7.1
Dynamic: author
Dynamic: license-file
